{
  "schemaVersion": "orbit360-final-block1-static-preflight-authorization-v16-first-visible-directory-fix",
  "issuedAt": "2026-07-21",
  "authorizationId": "final-block1-static-preflight-v1",
  "authorizationRevision": 16,
  "action": "final_block1_static_preflight_only",
  "repository": "paulaosoriof86/orbit360-core",
  "branch": "ays/backend-tenant-lab-v99-20260703",
  "tenantId": "alianzas-soluciones",
  "gateId": "block1-client360-insurers-lab-v20260717",
  "allowedExecutions": 1,
  "preflightRequired": true,
  "runtimeAllowed": false,
  "browserAllowed": false,
  "firestoreReadAllowed": false,
  "vaultReadAllowed": false,
  "secretsAllowed": false,
  "writesAllowed": false,
  "secretManagerWritesAllowed": false,
  "deployAllowed": false,
  "deploymentScope": "none",
  "functionsDeployAllowed": false,
  "rulesDeployAllowed": false,
  "productionAllowed": false,
  "reimportAllowed": false,
  "sourceInventory": {
    "runId": 29868538689,
    "ok": true,
    "clients": 414,
    "insurers": 26,
    "advisors": 7,
    "validReferences": 91,
    "pendingReferences": 2,
    "uniqueValidReferences": 91
  },
  "previousFinalGateEvidence": {
    "runId": 29884976786,
    "artifactId": 8516204588,
    "artifactDigest": "sha256:674e048034cbb2ad1a2951c5c92f03733b0a65ecd448383a2e81165a17629e61",
    "allRemoteBytesAndSha256Exact": true,
    "errorCode": "INSURER_INACTIVE_REASON_MISSING",
    "failureStage": "desktop_direction_client360",
    "writesExecuted": false,
    "productionTouched": false
  },
  "implementedFix": {
    "ok": true,
    "barrierCommit": "04737846f00780a50d1c9394371a37dbdee6e6dc",
    "ownerContractCommit": "8f225f6ccf9ca6b212a7621a09f67afce8745742",
    "documentationCommit": "1cf63378da8ab0758ab3c177b96fe9109e940429",
    "barrierVersion": "20260721.4",
    "directoryVisibilityRevision": "20260721.4a-first-visible-complete",
    "criticalRelease": "block1-critical-runtime-20260721-4",
    "directoryFirstPaintGuard": true,
    "pendingCssHidesDirectory": true,
    "synchronousOwnerBeforeRelease": true,
    "rendererChanged": false,
    "storeChanged": false,
    "dataChanged": false
  },
  "expected": {
    "contractVersion": "1.0.35",
    "preflightStatus": "GO_GATE_CONTRACT",
    "criticalRelease": "block1-critical-runtime-20260721-4",
    "criticalAssetCount": 9,
    "barrierVersion": "20260721.4",
    "directoryVisibilityRevision": "20260721.4a-first-visible-complete",
    "directoryFirstPaintGuard": true,
    "pendingCssHidesDirectory": true,
    "synchronousOwnerBeforeRelease": true,
    "architectureStatus": "GO_STATIC_ARCHITECTURE",
    "ownerContractStatus": "PASS",
    "ownerIdempotenceChecks": 27,
    "baseMutations": 1,
    "canonicalTransforms": 1,
    "followUpObserverDeliveries": 0,
    "writesExecuted": false,
    "runtimeExecuted": false,
    "browserExecuted": false,
    "deployExecuted": false,
    "productionTouched": false
  },
  "acceptance": "GO_GATE_CONTRACT_AND_STATIC_OK_TRUE_ONLY",
  "containsPII": false,
  "containsSecrets": false
}
